client/__init__.py
client/krm_client.py
krm_client/__init__.py
krm_client/krm_client.py
kubernetes_resource_monitor-1.0.4.dist-info/DESCRIPTION.rst
kubernetes_resource_monitor-1.0.4.dist-info/METADATA
kubernetes_resource_monitor-1.0.4.dist-info/RECORD
kubernetes_resource_monitor-1.0.4.dist-info/WHEEL
kubernetes_resource_monitor-1.0.4.dist-info/metadata.json
kubernetes_resource_monitor-1.0.4.dist-info/top_level.txt
