Metadata-Version: 2.0
Name: kubernetes-resource-monitor
Version: 1.0.4
Summary: Package contains a client that can be used to interface with KRM Api service.
Home-page: https://github.com/zhengwei143/kubernetes-resource-monitor
Author: Tan Zheng Wei
Author-email: tanzhengwei143@gmail.com
License: UNKNOWN
Platform: UNKNOWN
Classifier: Programming Language :: Python :: 3.6
Classifier: License :: OSI Approved :: GNU General Public License v3 (GPLv3)
Requires-Dist: kubernetes (==10.0.0)
Requires-Dist: pandas
